LICENSE
pynamodb_encoder/decoder.py
pynamodb_encoder/encoder.py
pynamodb_encoder/primitive_attribute_decoder.py
pynamodb_encoder/primitive_attribute_encoder.py
pynamodb_encoder-0.2.0.dist-info/LICENSE
pynamodb_encoder-0.2.0.dist-info/METADATA
pynamodb_encoder-0.2.0.dist-info/WHEEL
pynamodb_encoder-0.2.0.dist-info/RECORD
