Metadata-Version: 2.1
Name: pynamodb-encoder
Version: 0.2.0
Summary: Helper classes that encode/decode pynamodb models to/from JSON serializable dict
Home-page: https://github.com/lyang/pynamodb-encoder
License: MIT
Keywords: dynamodb,pynamodb,json,encode,decode
Author: Lin Yang
Author-email: github@linyang.me
Requires-Python: >=3.8,<4.0
Classifier: License :: OSI Approved :: MIT License
Classifier: Programming Language :: Python :: 3
Classifier: Programming Language :: Python :: 3.8
Classifier: Programming Language :: Python :: 3.9
Classifier: Programming Language :: Python :: 3.10
Classifier: Programming Language :: Python :: 3.11
Classifier: Programming Language :: Python :: 3.12
Requires-Dist: pynamodb (>=6.0.0,<7.0.0)
Project-URL: Repository, https://github.com/lyang/pynamodb-encoder
